profcomff_definitions/__init__.py
profcomff_definitions/base.py
profcomff_definitions/DM/README.md
profcomff_definitions/DM/__init__.py
profcomff_definitions/DM/infra_logs.py
profcomff_definitions/DM/marketing.py
profcomff_definitions/DM/monitoring.py
profcomff_definitions/DM/rating.py
profcomff_definitions/DM/rental.py
profcomff_definitions/DM/timetable.py
profcomff_definitions/DM/user.py
profcomff_definitions/DWH/README.md
profcomff_definitions/DWH/__init__.py
profcomff_definitions/DWH/auth_user.py
profcomff_definitions/DWH/rating.py
profcomff_definitions/DWH/rental.py
profcomff_definitions/DWH/user_info.py
profcomff_definitions/ODS/README.md
profcomff_definitions/ODS/__init__.py
profcomff_definitions/ODS/auth.py
profcomff_definitions/ODS/info.py
profcomff_definitions/ODS/infra_logs.py
profcomff_definitions/ODS/marketing.py
profcomff_definitions/ODS/mymsuapi.py
profcomff_definitions/ODS/rating.py
profcomff_definitions/ODS/rental.py
profcomff_definitions/ODS/social.py
profcomff_definitions/ODS/timetable.py
profcomff_definitions/STG/README.md
profcomff_definitions/STG/__init__.py
profcomff_definitions/STG/achievement.py
profcomff_definitions/STG/auth.py
profcomff_definitions/STG/dubinushka_manual.py
profcomff_definitions/STG/github.py
profcomff_definitions/STG/infra.py
profcomff_definitions/STG/marketing.py
profcomff_definitions/STG/mymsuapi.py
profcomff_definitions/STG/physics.py
profcomff_definitions/STG/pinger.py
profcomff_definitions/STG/print.py
profcomff_definitions/STG/rasphysmsu.py
profcomff_definitions/STG/rating.py
profcomff_definitions/STG/redirector.py
profcomff_definitions/STG/rental.py
profcomff_definitions/STG/services.py
profcomff_definitions/STG/social.py
profcomff_definitions/STG/timetable.py
profcomff_definitions/STG/union_member.py
profcomff_definitions/STG/userdata.py
profcomff_definitions-2025.4.21.1.dist-info/licenses/LICENSE
profcomff_definitions-2025.4.21.1.dist-info/METADATA
profcomff_definitions-2025.4.21.1.dist-info/WHEEL
profcomff_definitions-2025.4.21.1.dist-info/top_level.txt
profcomff_definitions-2025.4.21.1.dist-info/RECORD
