Metadata-Version: 2.4
Name: profcomff_definitions
Version: 2025.4.21.1
Summary: Data warehouse definitions and schemas
Author-email: "profcomff.com" <admin@profcomff.com>, Roman Dyakov <roman@dyakov.space>, Stanislav Roslavtsev <roslavtzev.stanislaw@yandex.ru>
License: BSD 3-Clause License
Project-URL: Homepage, https://app.profcomff.com
Project-URL: Documentation, https://github.com/profcomff/dwh-definitions/blob/main/README.md
Project-URL: Repository, https://github.com/profcomff/dwh-definitions
Project-URL: Issues, https://github.com/profcomff/dwh-definitions/issues
Project-URL: Changelog, https://github.com/profcomff/dwh-definitions/releases
Classifier: Development Status :: 5 - Production/Stable
Classifier: Programming Language :: Python :: 3
Classifier: Programming Language :: Python :: 3.10
Classifier: Programming Language :: Python :: 3.11
Requires-Python: >=3.10
License-File: LICENSE
Requires-Dist: SQLAlchemy
Requires-Dist: psycopg2-binary
Requires-Dist: alembic
Provides-Extra: airflow
Requires-Dist: apache-airflow; extra == "airflow"
Provides-Extra: testing
Requires-Dist: pytest; extra == "testing"
Requires-Dist: pytest-cov; extra == "testing"
Requires-Dist: pytest-mock; extra == "testing"
Requires-Dist: httpx; extra == "testing"
Requires-Dist: requests; extra == "testing"
Provides-Extra: style
Requires-Dist: black; extra == "style"
Requires-Dist: isort; extra == "style"
Requires-Dist: pydocstyle; extra == "style"
Requires-Dist: autoflake; extra == "style"
Dynamic: license-file
